pencilpy/__init__.py
pencilpy/cartoon.py
pencilpy/pencil.py
pencilpy-1.0.2.dist-info/METADATA
pencilpy-1.0.2.dist-info/WHEEL
pencilpy-1.0.2.dist-info/top_level.txt
pencilpy-1.0.2.dist-info/RECORD
